agentmesh/__init__.py
agentmesh/cli/__init__.py
agentmesh/cli/main.py
agentmesh/governance/__init__.py
agentmesh/governance/audit.py
agentmesh/governance/compliance.py
agentmesh/governance/policy.py
agentmesh/governance/shadow.py
agentmesh/identity/__init__.py
agentmesh/identity/agent_id.py
agentmesh/identity/credentials.py
agentmesh/identity/delegation.py
agentmesh/identity/risk.py
agentmesh/identity/spiffe.py
agentmesh/identity/sponsor.py
agentmesh/reward/__init__.py
agentmesh/reward/engine.py
agentmesh/reward/learning.py
agentmesh/reward/scoring.py
agentmesh/trust/__init__.py
agentmesh/trust/bridge.py
agentmesh/trust/capability.py
agentmesh/trust/handshake.py
agentmesh_platform-1.0.0a1.dist-info/METADATA
agentmesh_platform-1.0.0a1.dist-info/WHEEL
agentmesh_platform-1.0.0a1.dist-info/entry_points.txt
agentmesh_platform-1.0.0a1.dist-info/licenses/LICENSE
agentmesh_platform-1.0.0a1.dist-info/RECORD
