Metadata-Version: 2.4
Name: agentmesh-platform
Version: 1.0.0a1
Summary: The Secure Nervous System for Cloud-Native Agent Ecosystems - Identity, Trust, Reward, Governance
Project-URL: Homepage, https://github.com/imran-siddique/agent-mesh
Project-URL: Documentation, https://github.com/imran-siddique/agent-mesh#readme
Project-URL: Repository, https://github.com/imran-siddique/agent-mesh
Project-URL: Issues, https://github.com/imran-siddique/agent-mesh/issues
Project-URL: Changelog, https://github.com/imran-siddique/agent-mesh/blob/master/CHANGELOG.md
Author-email: Imran Siddique <imran.siddique@microsoft.com>
License: Apache-2.0
License-File: LICENSE
Keywords: a2a,agents,ai,compliance,eu-ai-act,governance,hipaa,iatp,identity,mcp,security,soc2,trust,zero-trust
Classifier: Development Status :: 3 - Alpha
Classifier: Intended Audience :: Developers
Classifier: Intended Audience :: Information Technology
Classifier: License :: OSI Approved :: Apache Software License
Classifier: Programming Language :: Python :: 3
Classifier: Programming Language :: Python :: 3.11
Classifier: Programming Language :: Python :: 3.12
Classifier: Topic :: Security
Classifier: Topic :: Security :: Cryptography
Classifier: Topic :: Software Development :: Libraries :: Python Modules
Classifier: Topic :: System :: Systems Administration :: Authentication/Directory
Requires-Python: >=3.11
Requires-Dist: agent-os-kernel[iatp,nexus]>=1.2.0
Requires-Dist: aiohttp>=3.9.0
Requires-Dist: click>=8.1.0
Requires-Dist: cryptography>=42.0.0
Requires-Dist: httpx>=0.26.0
Requires-Dist: pydantic>=2.5.0
Requires-Dist: pynacl>=1.5.0
Requires-Dist: pyyaml>=6.0
Requires-Dist: rich>=13.0.0
Requires-Dist: structlog>=24.1.0
Provides-Extra: dev
Requires-Dist: black>=24.1.0; extra == 'dev'
Requires-Dist: mypy>=1.8.0; extra == 'dev'
Requires-Dist: pytest-asyncio>=0.23.0; extra == 'dev'
Requires-Dist: pytest-cov>=4.1.0; extra == 'dev'
Requires-Dist: pytest>=7.4.0; extra == 'dev'
Requires-Dist: ruff>=0.1.0; extra == 'dev'
Provides-Extra: server
Requires-Dist: fastapi>=0.109.0; extra == 'server'
Requires-Dist: uvicorn[standard]>=0.27.0; extra == 'server'
